key_mwe/__about__.py
key_mwe/__init__.py
key_mwe/bespoke_types.py
key_mwe/config.py
key_mwe/keyness_estimator.py
key_mwe/ngram_dict_tokeniser.py
key_mwe/npmi_estimator.py
key_mwe/text_preprocessor.py
key_mwe/workflow.py
key_mwe-0.0.4.dist-info/METADATA
key_mwe-0.0.4.dist-info/WHEEL
key_mwe-0.0.4.dist-info/licenses/LICENSE.txt
key_mwe-0.0.4.dist-info/RECORD
