Metadata-Version: 2.3
Name: key-mwe
Version: 0.0.4
Summary: Extracts keywords and multi-word expressions (MWE) using within corpus PMI, and estimates keyword and MWE Keyness using between corpora PMI.
Project-URL: Documentation, https://github.com/leobeeson/key-mwe/blob/master/README.md
Project-URL: Issues, https://github.com/leobeeson/key-mwe/issues
Project-URL: Source, https://github.com/leobeeson/key-mwe
Author-email: Francis Beeson <leobeeson@gmail.com>
License-Expression: MIT
License-File: LICENSE.txt
Keywords: collocations,keyness,multi-word expressions,mwe
Classifier: Development Status :: 4 - Beta
Classifier: Programming Language :: Python
Classifier: Programming Language :: Python :: 3.11
Classifier: Programming Language :: Python :: 3.12
Classifier: Programming Language :: Python :: Implementation :: CPython
Requires-Python: >=3.11
Requires-Dist: gensim>=4.3.2
